virapi/__init__.py
virapi/logger.py
virapi/plugin.py
virapi/response.py
virapi/state.py
virapi/status.py
virapi/virapi.py
virapi-0.1.0.dist-info/licenses/LICENSE
virapi-0.1.0.dist-info/METADATA
virapi-0.1.0.dist-info/WHEEL
virapi-0.1.0.dist-info/top_level.txt
virapi-0.1.0.dist-info/RECORD
