Metadata-Version: 2.4
Name: virapi
Version: 0.1.0
Summary: A light and fast ASGI web framework
Author-email: Víctor Gómez <mdsuanzes@gmail.com>
License-Expression: MIT
Project-URL: Homepage, https://github.com/victorgomez09/virapi
Project-URL: Repository, https://github.com/victorgomez09/virapi.git
Project-URL: Issues, https://github.com/victorgomez09/virapi/issues
Project-URL: Documentation, https://github.com/victorgomez09/virapi/blob/main/README.md
Keywords: asgi,web,framework,http,api
Requires-Python: >=3.9
License-File: LICENSE
Provides-Extra: dev
Requires-Dist: pytest>=7.0.0; extra == "dev"
Requires-Dist: pytest-asyncio>=0.21.0; extra == "dev"
Provides-Extra: cli
Requires-Dist: uvicorn>=0.20.0; extra == "cli"
Provides-Extra: validation
Requires-Dist: pydantic>=2.0.0; extra == "validation"
Dynamic: license-file
